plc_format_converter/__init__.py
plc_format_converter/cli.py
plc_format_converter/core/__init__.py
plc_format_converter/core/converter.py
plc_format_converter/core/models.py
plc_format_converter/formats/__init__.py
plc_format_converter/formats/acd_handler.py
plc_format_converter/formats/l5x_handler.py
plc_format_converter/utils/__init__.py
plc_format_converter/utils/git_optimization.py
plc_format_converter/utils/validation.py
plc_format_converter-2.1.2.dist-info/licenses/LICENSE
plc_format_converter-2.1.2.dist-info/METADATA
plc_format_converter-2.1.2.dist-info/WHEEL
plc_format_converter-2.1.2.dist-info/entry_points.txt
plc_format_converter-2.1.2.dist-info/top_level.txt
plc_format_converter-2.1.2.dist-info/RECORD
