Metadata-Version: 2.4
Name: plc-format-converter
Version: 2.1.2
Summary: Modern ACD ↔ L5X conversion library with industrial-grade validation and motion control support
Author-email: PLC-GPT Team <plc-gpt@example.com>
Maintainer-email: PLC-GPT Team <plc-gpt@example.com>
License: MIT
Project-URL: Homepage, https://github.com/plc-gpt/plc-format-converter
Project-URL: Documentation, https://plc-format-converter.readthedocs.io
Project-URL: Repository, https://github.com/plc-gpt/plc-format-converter.git
Project-URL: Issues, https://github.com/plc-gpt/plc-format-converter/issues
Project-URL: Changelog, https://github.com/plc-gpt/plc-format-converter/blob/main/CHANGELOG.md
Keywords: plc,automation,rockwell,acd,l5x,format-conversion,motion-control,safety-systems,industrial-automation
Classifier: Development Status :: 4 - Beta
Classifier: Intended Audience :: Developers
Classifier: Intended Audience :: Manufacturing
Classifier: License :: OSI Approved :: MIT License
Classifier: Operating System :: OS Independent
Classifier: Programming Language :: Python :: 3
Classifier: Programming Language :: Python :: 3.8
Classifier: Programming Language :: Python :: 3.9
Classifier: Programming Language :: Python :: 3.10
Classifier: Programming Language :: Python :: 3.11
Classifier: Programming Language :: Python :: 3.12
Classifier: Topic :: Scientific/Engineering
Classifier: Topic :: Software Development :: Libraries :: Python Modules
Classifier: Topic :: System :: Hardware
Classifier: Topic :: Utilities
Requires-Python: >=3.8
License-File: LICENSE
Requires-Dist: pydantic>=2.0.0
Requires-Dist: structlog>=22.0.0
Requires-Dist: pathlib-abc>=0.1.0
Requires-Dist: typing-extensions>=4.0.0
Requires-Dist: click>=8.0.0
Provides-Extra: dev
Requires-Dist: pytest>=7.0.0; extra == "dev"
Requires-Dist: pytest-cov>=4.0.0; extra == "dev"
Requires-Dist: pytest-asyncio>=0.20.0; extra == "dev"
Requires-Dist: ruff>=0.1.0; extra == "dev"
Requires-Dist: mypy>=1.0.0; extra == "dev"
Requires-Dist: black>=22.0.0; extra == "dev"
Requires-Dist: pre-commit>=2.20.0; extra == "dev"
Requires-Dist: twine>=4.0.0; extra == "dev"
Requires-Dist: build>=0.8.0; extra == "dev"
Provides-Extra: acd-tools
Requires-Dist: acd-tools>=0.2.0; extra == "acd-tools"
Provides-Extra: l5x
Requires-Dist: l5x>=1.6.0; extra == "l5x"
Requires-Dist: lxml>=4.9.0; extra == "l5x"
Provides-Extra: studio5000
Requires-Dist: pywin32>=227; platform_system == "Windows" and extra == "studio5000"
Provides-Extra: all
Requires-Dist: acd-tools>=0.2.0; extra == "all"
Requires-Dist: l5x>=1.6.0; extra == "all"
Requires-Dist: lxml>=4.9.0; extra == "all"
Requires-Dist: pywin32>=227; platform_system == "Windows" and extra == "all"
Dynamic: license-file
